{
    "id": "72157688400738464",
    "title": "Sara y Chema",
    "primaryPhoto": "24096058808",
    "photos": [
        {
            "id": "24096058808",
            "title": "Sara y Chema",
            "tags": "portada",
            "sizes": [
                {
                    "label": "Square",
                    "height": 75,
                    "width": 75,
                    "url": "https://farm5.staticflickr.com/4496/24096058808_fa9404286b_s.jpg"
                },
                {
                    "label": "Large Square",
                    "height": "150",
                    "width": "150",
                    "url": "https://farm5.staticflickr.com/4496/24096058808_fa9404286b_q.jpg"
                },
                {
                    "label": "Thumbnail",
                    "height": "75",
                    "width": "100",
                    "url": "https://farm5.staticflickr.com/4496/24096058808_fa9404286b_t.jpg"
                },
                {
                    "label": "Small",
                    "height": "180",
                    "width": "240",
                    "url": "https://farm5.staticflickr.com/4496/24096058808_fa9404286b_m.jpg"
                },
                {
                    "label": "Small 320",
                    "height": 240,
                    "width": "320",
                    "url": "https://farm5.staticflickr.com/4496/24096058808_fa9404286b_n.jpg"
                },
                {
                    "label": "Medium",
                    "height": "375",
                    "width": "500",
                    "url": "https://farm5.staticflickr.com/4496/24096058808_fa9404286b.jpg"
                },
                {
                    "label": "Medium 640",
                    "height": "480",
                    "width": "640",
                    "url": "https://farm5.staticflickr.com/4496/24096058808_fa9404286b_z.jpg"
                },
                {
                    "label": "Medium 800",
                    "height": 600,
                    "width": "800",
                    "url": "https://farm5.staticflickr.com/4496/24096058808_fa9404286b_c.jpg"
                },
                {
                    "label": "Large",
                    "height": "768",
                    "width": "1024",
                    "url": "https://farm5.staticflickr.com/4496/24096058808_fa9404286b_b.jpg"
                },
                {
                    "label": "Large 1600",
                    "height": 1200,
                    "width": "1600",
                    "url": "https://farm5.staticflickr.com/4496/24096058808_5b2720cb99_h.jpg"
                },
                {
                    "label": "Large 2048",
                    "height": 1536,
                    "width": "2048",
                    "url": "https://farm5.staticflickr.com/4496/24096058808_7eb84dd75a_k.jpg"
                },
                {
                    "label": "Original",
                    "height": "3456",
                    "width": "4608",
                    "url": "https://farm5.staticflickr.com/4496/24096058808_082d79780a_o.jpg"
                }
            ]
        },
        {
            "id": "37916340442",
            "title": "Sara y Chema",
            "tags": "",
            "sizes": [
                {
                    "label": "Square",
                    "height": 75,
                    "width": 75,
                    "url": "https://farm5.staticflickr.com/4477/37916340442_c71c601609_s.jpg"
                },
                {
                    "label": "Large Square",
                    "height": "150",
                    "width": "150",
                    "url": "https://farm5.staticflickr.com/4477/37916340442_c71c601609_q.jpg"
                },
                {
                    "label": "Thumbnail",
                    "height": "75",
                    "width": "100",
                    "url": "https://farm5.staticflickr.com/4477/37916340442_c71c601609_t.jpg"
                },
                {
                    "label": "Small",
                    "height": "180",
                    "width": "240",
                    "url": "https://farm5.staticflickr.com/4477/37916340442_c71c601609_m.jpg"
                },
                {
                    "label": "Small 320",
                    "height": 240,
                    "width": "320",
                    "url": "https://farm5.staticflickr.com/4477/37916340442_c71c601609_n.jpg"
                },
                {
                    "label": "Medium",
                    "height": "375",
                    "width": "500",
                    "url": "https://farm5.staticflickr.com/4477/37916340442_c71c601609.jpg"
                },
                {
                    "label": "Medium 640",
                    "height": "480",
                    "width": "640",
                    "url": "https://farm5.staticflickr.com/4477/37916340442_c71c601609_z.jpg"
                },
                {
                    "label": "Medium 800",
                    "height": 600,
                    "width": "800",
                    "url": "https://farm5.staticflickr.com/4477/37916340442_c71c601609_c.jpg"
                },
                {
                    "label": "Large",
                    "height": "768",
                    "width": "1024",
                    "url": "https://farm5.staticflickr.com/4477/37916340442_c71c601609_b.jpg"
                },
                {
                    "label": "Large 1600",
                    "height": 1200,
                    "width": "1600",
                    "url": "https://farm5.staticflickr.com/4477/37916340442_a3c2837065_h.jpg"
                },
                {
                    "label": "Large 2048",
                    "height": 1536,
                    "width": "2048",
                    "url": "https://farm5.staticflickr.com/4477/37916340442_6df756b00b_k.jpg"
                },
                {
                    "label": "Original",
                    "height": "3456",
                    "width": "4608",
                    "url": "https://farm5.staticflickr.com/4477/37916340442_e569a9eb1c_o.jpg"
                }
            ]
        },
        {
            "id": "24096029388",
            "title": "Sara y Chema",
            "tags": "",
            "sizes": [
                {
                    "label": "Square",
                    "height": 75,
                    "width": 75,
                    "url": "https://farm5.staticflickr.com/4474/24096029388_80fba61f5c_s.jpg"
                },
                {
                    "label": "Large Square",
                    "height": "150",
                    "width": "150",
                    "url": "https://farm5.staticflickr.com/4474/24096029388_80fba61f5c_q.jpg"
                },
                {
                    "label": "Thumbnail",
                    "height": "75",
                    "width": "100",
                    "url": "https://farm5.staticflickr.com/4474/24096029388_80fba61f5c_t.jpg"
                },
                {
                    "label": "Small",
                    "height": "180",
                    "width": "240",
                    "url": "https://farm5.staticflickr.com/4474/24096029388_80fba61f5c_m.jpg"
                },
                {
                    "label": "Small 320",
                    "height": 240,
                    "width": "320",
                    "url": "https://farm5.staticflickr.com/4474/24096029388_80fba61f5c_n.jpg"
                },
                {
                    "label": "Medium",
                    "height": "375",
                    "width": "500",
                    "url": "https://farm5.staticflickr.com/4474/24096029388_80fba61f5c.jpg"
                },
                {
                    "label": "Medium 640",
                    "height": "480",
                    "width": "640",
                    "url": "https://farm5.staticflickr.com/4474/24096029388_80fba61f5c_z.jpg"
                },
                {
                    "label": "Medium 800",
                    "height": 600,
                    "width": "800",
                    "url": "https://farm5.staticflickr.com/4474/24096029388_80fba61f5c_c.jpg"
                },
                {
                    "label": "Large",
                    "height": "768",
                    "width": "1024",
                    "url": "https://farm5.staticflickr.com/4474/24096029388_80fba61f5c_b.jpg"
                },
                {
                    "label": "Large 1600",
                    "height": 1200,
                    "width": "1600",
                    "url": "https://farm5.staticflickr.com/4474/24096029388_17951879c3_h.jpg"
                },
                {
                    "label": "Large 2048",
                    "height": 1536,
                    "width": "2048",
                    "url": "https://farm5.staticflickr.com/4474/24096029388_0425e6fe51_k.jpg"
                },
                {
                    "label": "Original",
                    "height": "3456",
                    "width": "4608",
                    "url": "https://farm5.staticflickr.com/4474/24096029388_1bb646dca8_o.jpg"
                }
            ]
        },
        {
            "id": "37916342112",
            "title": "Sara y Chema",
            "tags": "",
            "sizes": [
                {
                    "label": "Square",
                    "height": 75,
                    "width": 75,
                    "url": "https://farm5.staticflickr.com/4482/37916342112_53b46746c7_s.jpg"
                },
                {
                    "label": "Large Square",
                    "height": "150",
                    "width": "150",
                    "url": "https://farm5.staticflickr.com/4482/37916342112_53b46746c7_q.jpg"
                },
                {
                    "label": "Thumbnail",
                    "height": "75",
                    "width": "100",
                    "url": "https://farm5.staticflickr.com/4482/37916342112_53b46746c7_t.jpg"
                },
                {
                    "label": "Small",
                    "height": "180",
                    "width": "240",
                    "url": "https://farm5.staticflickr.com/4482/37916342112_53b46746c7_m.jpg"
                },
                {
                    "label": "Small 320",
                    "height": 240,
                    "width": "320",
                    "url": "https://farm5.staticflickr.com/4482/37916342112_53b46746c7_n.jpg"
                },
                {
                    "label": "Medium",
                    "height": "375",
                    "width": "500",
                    "url": "https://farm5.staticflickr.com/4482/37916342112_53b46746c7.jpg"
                },
                {
                    "label": "Medium 640",
                    "height": "480",
                    "width": "640",
                    "url": "https://farm5.staticflickr.com/4482/37916342112_53b46746c7_z.jpg"
                },
                {
                    "label": "Medium 800",
                    "height": 600,
                    "width": "800",
                    "url": "https://farm5.staticflickr.com/4482/37916342112_53b46746c7_c.jpg"
                },
                {
                    "label": "Large",
                    "height": "768",
                    "width": "1024",
                    "url": "https://farm5.staticflickr.com/4482/37916342112_53b46746c7_b.jpg"
                },
                {
                    "label": "Large 1600",
                    "height": 1200,
                    "width": "1600",
                    "url": "https://farm5.staticflickr.com/4482/37916342112_d9c3b892ab_h.jpg"
                },
                {
                    "label": "Large 2048",
                    "height": 1536,
                    "width": "2048",
                    "url": "https://farm5.staticflickr.com/4482/37916342112_041b902441_k.jpg"
                },
                {
                    "label": "Original",
                    "height": "3456",
                    "width": "4608",
                    "url": "https://farm5.staticflickr.com/4482/37916342112_279b34756b_o.jpg"
                }
            ]
        },
        {
            "id": "37237730364",
            "title": "Sara y Chema",
            "tags": "",
            "sizes": [
                {
                    "label": "Square",
                    "height": 75,
                    "width": 75,
                    "url": "https://farm5.staticflickr.com/4453/37237730364_fc853a3dd6_s.jpg"
                },
                {
                    "label": "Large Square",
                    "height": "150",
                    "width": "150",
                    "url": "https://farm5.staticflickr.com/4453/37237730364_fc853a3dd6_q.jpg"
                },
                {
                    "label": "Thumbnail",
                    "height": "75",
                    "width": "100",
                    "url": "https://farm5.staticflickr.com/4453/37237730364_fc853a3dd6_t.jpg"
                },
                {
                    "label": "Small",
                    "height": "180",
                    "width": "240",
                    "url": "https://farm5.staticflickr.com/4453/37237730364_fc853a3dd6_m.jpg"
                },
                {
                    "label": "Small 320",
                    "height": 240,
                    "width": "320",
                    "url": "https://farm5.staticflickr.com/4453/37237730364_fc853a3dd6_n.jpg"
                },
                {
                    "label": "Medium",
                    "height": "375",
                    "width": "500",
                    "url": "https://farm5.staticflickr.com/4453/37237730364_fc853a3dd6.jpg"
                },
                {
                    "label": "Medium 640",
                    "height": "480",
                    "width": "640",
                    "url": "https://farm5.staticflickr.com/4453/37237730364_fc853a3dd6_z.jpg"
                },
                {
                    "label": "Medium 800",
                    "height": 600,
                    "width": "800",
                    "url": "https://farm5.staticflickr.com/4453/37237730364_fc853a3dd6_c.jpg"
                },
                {
                    "label": "Large",
                    "height": "768",
                    "width": "1024",
                    "url": "https://farm5.staticflickr.com/4453/37237730364_fc853a3dd6_b.jpg"
                },
                {
                    "label": "Large 1600",
                    "height": 1200,
                    "width": "1600",
                    "url": "https://farm5.staticflickr.com/4453/37237730364_fa09807f80_h.jpg"
                },
                {
                    "label": "Large 2048",
                    "height": 1536,
                    "width": "2048",
                    "url": "https://farm5.staticflickr.com/4453/37237730364_cddb5ea51e_k.jpg"
                },
                {
                    "label": "Original",
                    "height": "3456",
                    "width": "4608",
                    "url": "https://farm5.staticflickr.com/4453/37237730364_fb3986c9f2_o.jpg"
                }
            ]
        },
        {
            "id": "37916344272",
            "title": "Sara y Chema",
            "tags": "",
            "sizes": [
                {
                    "label": "Square",
                    "height": 75,
                    "width": 75,
                    "url": "https://farm5.staticflickr.com/4498/37916344272_83ecde63c1_s.jpg"
                },
                {
                    "label": "Large Square",
                    "height": "150",
                    "width": "150",
                    "url": "https://farm5.staticflickr.com/4498/37916344272_83ecde63c1_q.jpg"
                },
                {
                    "label": "Thumbnail",
                    "height": "100",
                    "width": "75",
                    "url": "https://farm5.staticflickr.com/4498/37916344272_83ecde63c1_t.jpg"
                },
                {
                    "label": "Small",
                    "height": "240",
                    "width": "180",
                    "url": "https://farm5.staticflickr.com/4498/37916344272_83ecde63c1_m.jpg"
                },
                {
                    "label": "Small 320",
                    "height": "320",
                    "width": 240,
                    "url": "https://farm5.staticflickr.com/4498/37916344272_83ecde63c1_n.jpg"
                },
                {
                    "label": "Medium",
                    "height": "500",
                    "width": "375",
                    "url": "https://farm5.staticflickr.com/4498/37916344272_83ecde63c1.jpg"
                },
                {
                    "label": "Medium 640",
                    "height": "640",
                    "width": "480",
                    "url": "https://farm5.staticflickr.com/4498/37916344272_83ecde63c1_z.jpg"
                },
                {
                    "label": "Medium 800",
                    "height": "800",
                    "width": 600,
                    "url": "https://farm5.staticflickr.com/4498/37916344272_83ecde63c1_c.jpg"
                },
                {
                    "label": "Large",
                    "height": "1024",
                    "width": "768",
                    "url": "https://farm5.staticflickr.com/4498/37916344272_83ecde63c1_b.jpg"
                },
                {
                    "label": "Large 1600",
                    "height": "1600",
                    "width": 1200,
                    "url": "https://farm5.staticflickr.com/4498/37916344272_706a2b1508_h.jpg"
                },
                {
                    "label": "Large 2048",
                    "height": "2048",
                    "width": 1536,
                    "url": "https://farm5.staticflickr.com/4498/37916344272_b57a75e03f_k.jpg"
                },
                {
                    "label": "Original",
                    "height": "4608",
                    "width": "3456",
                    "url": "https://farm5.staticflickr.com/4498/37916344272_11d1680151_o.jpg"
                }
            ]
        },
        {
            "id": "37947100421",
            "title": "Sara y Chema",
            "tags": "",
            "sizes": [
                {
                    "label": "Square",
                    "height": 75,
                    "width": 75,
                    "url": "https://farm5.staticflickr.com/4495/37947100421_65d1b44497_s.jpg"
                },
                {
                    "label": "Large Square",
                    "height": "150",
                    "width": "150",
                    "url": "https://farm5.staticflickr.com/4495/37947100421_65d1b44497_q.jpg"
                },
                {
                    "label": "Thumbnail",
                    "height": "75",
                    "width": "100",
                    "url": "https://farm5.staticflickr.com/4495/37947100421_65d1b44497_t.jpg"
                },
                {
                    "label": "Small",
                    "height": "180",
                    "width": "240",
                    "url": "https://farm5.staticflickr.com/4495/37947100421_65d1b44497_m.jpg"
                },
                {
                    "label": "Small 320",
                    "height": 240,
                    "width": "320",
                    "url": "https://farm5.staticflickr.com/4495/37947100421_65d1b44497_n.jpg"
                },
                {
                    "label": "Medium",
                    "height": "375",
                    "width": "500",
                    "url": "https://farm5.staticflickr.com/4495/37947100421_65d1b44497.jpg"
                },
                {
                    "label": "Medium 640",
                    "height": "480",
                    "width": "640",
                    "url": "https://farm5.staticflickr.com/4495/37947100421_65d1b44497_z.jpg"
                },
                {
                    "label": "Medium 800",
                    "height": 600,
                    "width": "800",
                    "url": "https://farm5.staticflickr.com/4495/37947100421_65d1b44497_c.jpg"
                },
                {
                    "label": "Large",
                    "height": "768",
                    "width": "1024",
                    "url": "https://farm5.staticflickr.com/4495/37947100421_65d1b44497_b.jpg"
                },
                {
                    "label": "Large 1600",
                    "height": 1200,
                    "width": "1600",
                    "url": "https://farm5.staticflickr.com/4495/37947100421_2ab9d841a1_h.jpg"
                },
                {
                    "label": "Large 2048",
                    "height": 1536,
                    "width": "2048",
                    "url": "https://farm5.staticflickr.com/4495/37947100421_6d407e7e1d_k.jpg"
                },
                {
                    "label": "Original",
                    "height": "3456",
                    "width": "4608",
                    "url": "https://farm5.staticflickr.com/4495/37947100421_ea34fb41e2_o.jpg"
                }
            ]
        },
        {
            "id": "37893896786",
            "title": "Sara y Chema",
            "tags": "",
            "sizes": [
                {
                    "label": "Square",
                    "height": 75,
                    "width": 75,
                    "url": "https://farm5.staticflickr.com/4497/37893896786_c26be0588d_s.jpg"
                },
                {
                    "label": "Large Square",
                    "height": "150",
                    "width": "150",
                    "url": "https://farm5.staticflickr.com/4497/37893896786_c26be0588d_q.jpg"
                },
                {
                    "label": "Thumbnail",
                    "height": "75",
                    "width": "100",
                    "url": "https://farm5.staticflickr.com/4497/37893896786_c26be0588d_t.jpg"
                },
                {
                    "label": "Small",
                    "height": "180",
                    "width": "240",
                    "url": "https://farm5.staticflickr.com/4497/37893896786_c26be0588d_m.jpg"
                },
                {
                    "label": "Small 320",
                    "height": 240,
                    "width": "320",
                    "url": "https://farm5.staticflickr.com/4497/37893896786_c26be0588d_n.jpg"
                },
                {
                    "label": "Medium",
                    "height": "375",
                    "width": "500",
                    "url": "https://farm5.staticflickr.com/4497/37893896786_c26be0588d.jpg"
                },
                {
                    "label": "Medium 640",
                    "height": "480",
                    "width": "640",
                    "url": "https://farm5.staticflickr.com/4497/37893896786_c26be0588d_z.jpg"
                },
                {
                    "label": "Medium 800",
                    "height": 600,
                    "width": "800",
                    "url": "https://farm5.staticflickr.com/4497/37893896786_c26be0588d_c.jpg"
                },
                {
                    "label": "Large",
                    "height": "768",
                    "width": "1024",
                    "url": "https://farm5.staticflickr.com/4497/37893896786_c26be0588d_b.jpg"
                },
                {
                    "label": "Large 1600",
                    "height": 1200,
                    "width": "1600",
                    "url": "https://farm5.staticflickr.com/4497/37893896786_d7ec47ca56_h.jpg"
                },
                {
                    "label": "Large 2048",
                    "height": 1536,
                    "width": "2048",
                    "url": "https://farm5.staticflickr.com/4497/37893896786_7718d3a343_k.jpg"
                },
                {
                    "label": "Original",
                    "height": "3456",
                    "width": "4608",
                    "url": "https://farm5.staticflickr.com/4497/37893896786_58e6d1098f_o.jpg"
                }
            ]
        },
        {
            "id": "37947105121",
            "title": "Sara y Chema",
            "tags": "",
            "sizes": [
                {
                    "label": "Square",
                    "height": 75,
                    "width": 75,
                    "url": "https://farm5.staticflickr.com/4454/37947105121_f2ed2719c3_s.jpg"
                },
                {
                    "label": "Large Square",
                    "height": "150",
                    "width": "150",
                    "url": "https://farm5.staticflickr.com/4454/37947105121_f2ed2719c3_q.jpg"
                },
                {
                    "label": "Thumbnail",
                    "height": "75",
                    "width": "100",
                    "url": "https://farm5.staticflickr.com/4454/37947105121_f2ed2719c3_t.jpg"
                },
                {
                    "label": "Small",
                    "height": "180",
                    "width": "240",
                    "url": "https://farm5.staticflickr.com/4454/37947105121_f2ed2719c3_m.jpg"
                },
                {
                    "label": "Small 320",
                    "height": 240,
                    "width": "320",
                    "url": "https://farm5.staticflickr.com/4454/37947105121_f2ed2719c3_n.jpg"
                },
                {
                    "label": "Medium",
                    "height": "375",
                    "width": "500",
                    "url": "https://farm5.staticflickr.com/4454/37947105121_f2ed2719c3.jpg"
                },
                {
                    "label": "Medium 640",
                    "height": "480",
                    "width": "640",
                    "url": "https://farm5.staticflickr.com/4454/37947105121_f2ed2719c3_z.jpg"
                },
                {
                    "label": "Medium 800",
                    "height": 600,
                    "width": "800",
                    "url": "https://farm5.staticflickr.com/4454/37947105121_f2ed2719c3_c.jpg"
                },
                {
                    "label": "Large",
                    "height": "768",
                    "width": "1024",
                    "url": "https://farm5.staticflickr.com/4454/37947105121_f2ed2719c3_b.jpg"
                },
                {
                    "label": "Large 1600",
                    "height": 1200,
                    "width": "1600",
                    "url": "https://farm5.staticflickr.com/4454/37947105121_11e4ebd8fc_h.jpg"
                },
                {
                    "label": "Large 2048",
                    "height": 1536,
                    "width": "2048",
                    "url": "https://farm5.staticflickr.com/4454/37947105121_1cf9dfa2d6_k.jpg"
                },
                {
                    "label": "Original",
                    "height": "3456",
                    "width": "4608",
                    "url": "https://farm5.staticflickr.com/4454/37947105121_f2883803b7_o.jpg"
                }
            ]
        },
        {
            "id": "37947108011",
            "title": "Sara y Chema",
            "tags": "",
            "sizes": [
                {
                    "label": "Square",
                    "height": 75,
                    "width": 75,
                    "url": "https://farm5.staticflickr.com/4495/37947108011_d319c0c55c_s.jpg"
                },
                {
                    "label": "Large Square",
                    "height": "150",
                    "width": "150",
                    "url": "https://farm5.staticflickr.com/4495/37947108011_d319c0c55c_q.jpg"
                },
                {
                    "label": "Thumbnail",
                    "height": "75",
                    "width": "100",
                    "url": "https://farm5.staticflickr.com/4495/37947108011_d319c0c55c_t.jpg"
                },
                {
                    "label": "Small",
                    "height": "180",
                    "width": "240",
                    "url": "https://farm5.staticflickr.com/4495/37947108011_d319c0c55c_m.jpg"
                },
                {
                    "label": "Small 320",
                    "height": 240,
                    "width": "320",
                    "url": "https://farm5.staticflickr.com/4495/37947108011_d319c0c55c_n.jpg"
                },
                {
                    "label": "Medium",
                    "height": "375",
                    "width": "500",
                    "url": "https://farm5.staticflickr.com/4495/37947108011_d319c0c55c.jpg"
                },
                {
                    "label": "Medium 640",
                    "height": "480",
                    "width": "640",
                    "url": "https://farm5.staticflickr.com/4495/37947108011_d319c0c55c_z.jpg"
                },
                {
                    "label": "Medium 800",
                    "height": 600,
                    "width": "800",
                    "url": "https://farm5.staticflickr.com/4495/37947108011_d319c0c55c_c.jpg"
                },
                {
                    "label": "Large",
                    "height": "768",
                    "width": "1024",
                    "url": "https://farm5.staticflickr.com/4495/37947108011_d319c0c55c_b.jpg"
                },
                {
                    "label": "Large 1600",
                    "height": 1200,
                    "width": "1600",
                    "url": "https://farm5.staticflickr.com/4495/37947108011_fba5b9e7f4_h.jpg"
                },
                {
                    "label": "Large 2048",
                    "height": 1536,
                    "width": "2048",
                    "url": "https://farm5.staticflickr.com/4495/37947108011_72141a3b06_k.jpg"
                },
                {
                    "label": "Original",
                    "height": "3456",
                    "width": "4608",
                    "url": "https://farm5.staticflickr.com/4495/37947108011_f411d2ccf9_o.jpg"
                }
            ]
        },
        {
            "id": "37947110601",
            "title": "Sara y Chema",
            "tags": "",
            "sizes": [
                {
                    "label": "Square",
                    "height": 75,
                    "width": 75,
                    "url": "https://farm5.staticflickr.com/4461/37947110601_fd222b9a1e_s.jpg"
                },
                {
                    "label": "Large Square",
                    "height": "150",
                    "width": "150",
                    "url": "https://farm5.staticflickr.com/4461/37947110601_fd222b9a1e_q.jpg"
                },
                {
                    "label": "Thumbnail",
                    "height": "100",
                    "width": "75",
                    "url": "https://farm5.staticflickr.com/4461/37947110601_fd222b9a1e_t.jpg"
                },
                {
                    "label": "Small",
                    "height": "240",
                    "width": "180",
                    "url": "https://farm5.staticflickr.com/4461/37947110601_fd222b9a1e_m.jpg"
                },
                {
                    "label": "Small 320",
                    "height": "320",
                    "width": 240,
                    "url": "https://farm5.staticflickr.com/4461/37947110601_fd222b9a1e_n.jpg"
                },
                {
                    "label": "Medium",
                    "height": "500",
                    "width": "375",
                    "url": "https://farm5.staticflickr.com/4461/37947110601_fd222b9a1e.jpg"
                },
                {
                    "label": "Medium 640",
                    "height": "640",
                    "width": "480",
                    "url": "https://farm5.staticflickr.com/4461/37947110601_fd222b9a1e_z.jpg"
                },
                {
                    "label": "Medium 800",
                    "height": "800",
                    "width": 600,
                    "url": "https://farm5.staticflickr.com/4461/37947110601_fd222b9a1e_c.jpg"
                },
                {
                    "label": "Large",
                    "height": "1024",
                    "width": "768",
                    "url": "https://farm5.staticflickr.com/4461/37947110601_fd222b9a1e_b.jpg"
                },
                {
                    "label": "Large 1600",
                    "height": "1600",
                    "width": 1200,
                    "url": "https://farm5.staticflickr.com/4461/37947110601_3b47d53a39_h.jpg"
                },
                {
                    "label": "Large 2048",
                    "height": "2048",
                    "width": 1536,
                    "url": "https://farm5.staticflickr.com/4461/37947110601_ffa7f0a42a_k.jpg"
                },
                {
                    "label": "Original",
                    "height": "4608",
                    "width": "3456",
                    "url": "https://farm5.staticflickr.com/4461/37947110601_33921191b7_o.jpg"
                }
            ]
        },
        {
            "id": "37947112411",
            "title": "Sara y Chema",
            "tags": "",
            "sizes": [
                {
                    "label": "Square",
                    "height": 75,
                    "width": 75,
                    "url": "https://farm5.staticflickr.com/4461/37947112411_fd4c34f18d_s.jpg"
                },
                {
                    "label": "Large Square",
                    "height": "150",
                    "width": "150",
                    "url": "https://farm5.staticflickr.com/4461/37947112411_fd4c34f18d_q.jpg"
                },
                {
                    "label": "Thumbnail",
                    "height": "73",
                    "width": "100",
                    "url": "https://farm5.staticflickr.com/4461/37947112411_fd4c34f18d_t.jpg"
                },
                {
                    "label": "Small",
                    "height": "175",
                    "width": "240",
                    "url": "https://farm5.staticflickr.com/4461/37947112411_fd4c34f18d_m.jpg"
                },
                {
                    "label": "Small 320",
                    "height": 233,
                    "width": "320",
                    "url": "https://farm5.staticflickr.com/4461/37947112411_fd4c34f18d_n.jpg"
                },
                {
                    "label": "Medium",
                    "height": "364",
                    "width": "500",
                    "url": "https://farm5.staticflickr.com/4461/37947112411_fd4c34f18d.jpg"
                },
                {
                    "label": "Medium 640",
                    "height": "466",
                    "width": "640",
                    "url": "https://farm5.staticflickr.com/4461/37947112411_fd4c34f18d_z.jpg"
                },
                {
                    "label": "Medium 800",
                    "height": 583,
                    "width": "800",
                    "url": "https://farm5.staticflickr.com/4461/37947112411_fd4c34f18d_c.jpg"
                },
                {
                    "label": "Large",
                    "height": "746",
                    "width": "1024",
                    "url": "https://farm5.staticflickr.com/4461/37947112411_fd4c34f18d_b.jpg"
                },
                {
                    "label": "Large 1600",
                    "height": 1166,
                    "width": "1600",
                    "url": "https://farm5.staticflickr.com/4461/37947112411_40a8b79754_h.jpg"
                },
                {
                    "label": "Large 2048",
                    "height": 1493,
                    "width": "2048",
                    "url": "https://farm5.staticflickr.com/4461/37947112411_d2c13ca524_k.jpg"
                },
                {
                    "label": "Original",
                    "height": "3119",
                    "width": "4279",
                    "url": "https://farm5.staticflickr.com/4461/37947112411_0fe4f8fd65_o.jpg"
                }
            ]
        },
        {
            "id": "37237746494",
            "title": "Sara y Chema",
            "tags": "",
            "sizes": [
                {
                    "label": "Square",
                    "height": 75,
                    "width": 75,
                    "url": "https://farm5.staticflickr.com/4488/37237746494_4a1a82ff58_s.jpg"
                },
                {
                    "label": "Large Square",
                    "height": "150",
                    "width": "150",
                    "url": "https://farm5.staticflickr.com/4488/37237746494_4a1a82ff58_q.jpg"
                },
                {
                    "label": "Thumbnail",
                    "height": "75",
                    "width": "100",
                    "url": "https://farm5.staticflickr.com/4488/37237746494_4a1a82ff58_t.jpg"
                },
                {
                    "label": "Small",
                    "height": "180",
                    "width": "240",
                    "url": "https://farm5.staticflickr.com/4488/37237746494_4a1a82ff58_m.jpg"
                },
                {
                    "label": "Small 320",
                    "height": 240,
                    "width": "320",
                    "url": "https://farm5.staticflickr.com/4488/37237746494_4a1a82ff58_n.jpg"
                },
                {
                    "label": "Medium",
                    "height": "375",
                    "width": "500",
                    "url": "https://farm5.staticflickr.com/4488/37237746494_4a1a82ff58.jpg"
                },
                {
                    "label": "Medium 640",
                    "height": "480",
                    "width": "640",
                    "url": "https://farm5.staticflickr.com/4488/37237746494_4a1a82ff58_z.jpg"
                },
                {
                    "label": "Medium 800",
                    "height": 600,
                    "width": "800",
                    "url": "https://farm5.staticflickr.com/4488/37237746494_4a1a82ff58_c.jpg"
                },
                {
                    "label": "Large",
                    "height": "768",
                    "width": "1024",
                    "url": "https://farm5.staticflickr.com/4488/37237746494_4a1a82ff58_b.jpg"
                },
                {
                    "label": "Large 1600",
                    "height": 1200,
                    "width": "1600",
                    "url": "https://farm5.staticflickr.com/4488/37237746494_776e97f143_h.jpg"
                },
                {
                    "label": "Large 2048",
                    "height": 1536,
                    "width": "2048",
                    "url": "https://farm5.staticflickr.com/4488/37237746494_2f71224ce9_k.jpg"
                },
                {
                    "label": "Original",
                    "height": "3456",
                    "width": "4608",
                    "url": "https://farm5.staticflickr.com/4488/37237746494_8e641dd301_o.jpg"
                }
            ]
        },
        {
            "id": "37893905426",
            "title": "Sara y Chema",
            "tags": "",
            "sizes": [
                {
                    "label": "Square",
                    "height": 75,
                    "width": 75,
                    "url": "https://farm5.staticflickr.com/4443/37893905426_c2a429ac41_s.jpg"
                },
                {
                    "label": "Large Square",
                    "height": "150",
                    "width": "150",
                    "url": "https://farm5.staticflickr.com/4443/37893905426_c2a429ac41_q.jpg"
                },
                {
                    "label": "Thumbnail",
                    "height": "75",
                    "width": "100",
                    "url": "https://farm5.staticflickr.com/4443/37893905426_c2a429ac41_t.jpg"
                },
                {
                    "label": "Small",
                    "height": "180",
                    "width": "240",
                    "url": "https://farm5.staticflickr.com/4443/37893905426_c2a429ac41_m.jpg"
                },
                {
                    "label": "Small 320",
                    "height": 240,
                    "width": "320",
                    "url": "https://farm5.staticflickr.com/4443/37893905426_c2a429ac41_n.jpg"
                },
                {
                    "label": "Medium",
                    "height": "375",
                    "width": "500",
                    "url": "https://farm5.staticflickr.com/4443/37893905426_c2a429ac41.jpg"
                },
                {
                    "label": "Medium 640",
                    "height": "480",
                    "width": "640",
                    "url": "https://farm5.staticflickr.com/4443/37893905426_c2a429ac41_z.jpg"
                },
                {
                    "label": "Medium 800",
                    "height": 600,
                    "width": "800",
                    "url": "https://farm5.staticflickr.com/4443/37893905426_c2a429ac41_c.jpg"
                },
                {
                    "label": "Large",
                    "height": "768",
                    "width": "1024",
                    "url": "https://farm5.staticflickr.com/4443/37893905426_c2a429ac41_b.jpg"
                },
                {
                    "label": "Large 1600",
                    "height": 1200,
                    "width": "1600",
                    "url": "https://farm5.staticflickr.com/4443/37893905426_22dcfe80be_h.jpg"
                },
                {
                    "label": "Large 2048",
                    "height": 1536,
                    "width": "2048",
                    "url": "https://farm5.staticflickr.com/4443/37893905426_a087bed099_k.jpg"
                },
                {
                    "label": "Original",
                    "height": "3456",
                    "width": "4608",
                    "url": "https://farm5.staticflickr.com/4443/37893905426_332187e56a_o.jpg"
                }
            ]
        },
        {
            "id": "37947118571",
            "title": "Sara y Chema",
            "tags": "",
            "sizes": [
                {
                    "label": "Square",
                    "height": 75,
                    "width": 75,
                    "url": "https://farm5.staticflickr.com/4443/37947118571_9432e5f241_s.jpg"
                },
                {
                    "label": "Large Square",
                    "height": "150",
                    "width": "150",
                    "url": "https://farm5.staticflickr.com/4443/37947118571_9432e5f241_q.jpg"
                },
                {
                    "label": "Thumbnail",
                    "height": "75",
                    "width": "100",
                    "url": "https://farm5.staticflickr.com/4443/37947118571_9432e5f241_t.jpg"
                },
                {
                    "label": "Small",
                    "height": "180",
                    "width": "240",
                    "url": "https://farm5.staticflickr.com/4443/37947118571_9432e5f241_m.jpg"
                },
                {
                    "label": "Small 320",
                    "height": 240,
                    "width": "320",
                    "url": "https://farm5.staticflickr.com/4443/37947118571_9432e5f241_n.jpg"
                },
                {
                    "label": "Medium",
                    "height": "375",
                    "width": "500",
                    "url": "https://farm5.staticflickr.com/4443/37947118571_9432e5f241.jpg"
                },
                {
                    "label": "Medium 640",
                    "height": "480",
                    "width": "640",
                    "url": "https://farm5.staticflickr.com/4443/37947118571_9432e5f241_z.jpg"
                },
                {
                    "label": "Medium 800",
                    "height": 600,
                    "width": "800",
                    "url": "https://farm5.staticflickr.com/4443/37947118571_9432e5f241_c.jpg"
                },
                {
                    "label": "Large",
                    "height": "768",
                    "width": "1024",
                    "url": "https://farm5.staticflickr.com/4443/37947118571_9432e5f241_b.jpg"
                },
                {
                    "label": "Large 1600",
                    "height": 1200,
                    "width": "1600",
                    "url": "https://farm5.staticflickr.com/4443/37947118571_532e4e2517_h.jpg"
                },
                {
                    "label": "Large 2048",
                    "height": 1536,
                    "width": "2048",
                    "url": "https://farm5.staticflickr.com/4443/37947118571_a4568e7b3e_k.jpg"
                },
                {
                    "label": "Original",
                    "height": "3456",
                    "width": "4608",
                    "url": "https://farm5.staticflickr.com/4443/37947118571_b1266cf2d1_o.jpg"
                }
            ]
        },
        {
            "id": "24096055038",
            "title": "Sara y Chema",
            "tags": "",
            "sizes": [
                {
                    "label": "Square",
                    "height": 75,
                    "width": 75,
                    "url": "https://farm5.staticflickr.com/4509/24096055038_194431cd74_s.jpg"
                },
                {
                    "label": "Large Square",
                    "height": "150",
                    "width": "150",
                    "url": "https://farm5.staticflickr.com/4509/24096055038_194431cd74_q.jpg"
                },
                {
                    "label": "Thumbnail",
                    "height": "75",
                    "width": "100",
                    "url": "https://farm5.staticflickr.com/4509/24096055038_194431cd74_t.jpg"
                },
                {
                    "label": "Small",
                    "height": "180",
                    "width": "240",
                    "url": "https://farm5.staticflickr.com/4509/24096055038_194431cd74_m.jpg"
                },
                {
                    "label": "Small 320",
                    "height": 240,
                    "width": "320",
                    "url": "https://farm5.staticflickr.com/4509/24096055038_194431cd74_n.jpg"
                },
                {
                    "label": "Medium",
                    "height": "375",
                    "width": "500",
                    "url": "https://farm5.staticflickr.com/4509/24096055038_194431cd74.jpg"
                },
                {
                    "label": "Medium 640",
                    "height": "480",
                    "width": "640",
                    "url": "https://farm5.staticflickr.com/4509/24096055038_194431cd74_z.jpg"
                },
                {
                    "label": "Medium 800",
                    "height": 600,
                    "width": "800",
                    "url": "https://farm5.staticflickr.com/4509/24096055038_194431cd74_c.jpg"
                },
                {
                    "label": "Large",
                    "height": "768",
                    "width": "1024",
                    "url": "https://farm5.staticflickr.com/4509/24096055038_194431cd74_b.jpg"
                },
                {
                    "label": "Large 1600",
                    "height": 1200,
                    "width": "1600",
                    "url": "https://farm5.staticflickr.com/4509/24096055038_a9541235d3_h.jpg"
                },
                {
                    "label": "Large 2048",
                    "height": 1536,
                    "width": "2048",
                    "url": "https://farm5.staticflickr.com/4509/24096055038_931988d011_k.jpg"
                },
                {
                    "label": "Original",
                    "height": "3456",
                    "width": "4608",
                    "url": "https://farm5.staticflickr.com/4509/24096055038_261f382828_o.jpg"
                }
            ]
        },
        {
            "id": "37947122681",
            "title": "Sara y Chema",
            "tags": "",
            "sizes": [
                {
                    "label": "Square",
                    "height": 75,
                    "width": 75,
                    "url": "https://farm5.staticflickr.com/4448/37947122681_5ffa253ecf_s.jpg"
                },
                {
                    "label": "Large Square",
                    "height": "150",
                    "width": "150",
                    "url": "https://farm5.staticflickr.com/4448/37947122681_5ffa253ecf_q.jpg"
                },
                {
                    "label": "Thumbnail",
                    "height": "75",
                    "width": "100",
                    "url": "https://farm5.staticflickr.com/4448/37947122681_5ffa253ecf_t.jpg"
                },
                {
                    "label": "Small",
                    "height": "180",
                    "width": "240",
                    "url": "https://farm5.staticflickr.com/4448/37947122681_5ffa253ecf_m.jpg"
                },
                {
                    "label": "Small 320",
                    "height": 240,
                    "width": "320",
                    "url": "https://farm5.staticflickr.com/4448/37947122681_5ffa253ecf_n.jpg"
                },
                {
                    "label": "Medium",
                    "height": "375",
                    "width": "500",
                    "url": "https://farm5.staticflickr.com/4448/37947122681_5ffa253ecf.jpg"
                },
                {
                    "label": "Medium 640",
                    "height": "480",
                    "width": "640",
                    "url": "https://farm5.staticflickr.com/4448/37947122681_5ffa253ecf_z.jpg"
                },
                {
                    "label": "Medium 800",
                    "height": 600,
                    "width": "800",
                    "url": "https://farm5.staticflickr.com/4448/37947122681_5ffa253ecf_c.jpg"
                },
                {
                    "label": "Large",
                    "height": "768",
                    "width": "1024",
                    "url": "https://farm5.staticflickr.com/4448/37947122681_5ffa253ecf_b.jpg"
                },
                {
                    "label": "Large 1600",
                    "height": 1200,
                    "width": "1600",
                    "url": "https://farm5.staticflickr.com/4448/37947122681_bff80d5791_h.jpg"
                },
                {
                    "label": "Large 2048",
                    "height": 1536,
                    "width": "2048",
                    "url": "https://farm5.staticflickr.com/4448/37947122681_e003e96087_k.jpg"
                },
                {
                    "label": "Original",
                    "height": "3456",
                    "width": "4608",
                    "url": "https://farm5.staticflickr.com/4448/37947122681_cc09c0ea3b_o.jpg"
                }
            ]
        },
        {
            "id": "24096057338",
            "title": "Sara y Chema",
            "tags": "",
            "sizes": [
                {
                    "label": "Square",
                    "height": 75,
                    "width": 75,
                    "url": "https://farm5.staticflickr.com/4497/24096057338_f00c2c0a03_s.jpg"
                },
                {
                    "label": "Large Square",
                    "height": "150",
                    "width": "150",
                    "url": "https://farm5.staticflickr.com/4497/24096057338_f00c2c0a03_q.jpg"
                },
                {
                    "label": "Thumbnail",
                    "height": "100",
                    "width": "75",
                    "url": "https://farm5.staticflickr.com/4497/24096057338_f00c2c0a03_t.jpg"
                },
                {
                    "label": "Small",
                    "height": "240",
                    "width": "180",
                    "url": "https://farm5.staticflickr.com/4497/24096057338_f00c2c0a03_m.jpg"
                },
                {
                    "label": "Small 320",
                    "height": "320",
                    "width": 240,
                    "url": "https://farm5.staticflickr.com/4497/24096057338_f00c2c0a03_n.jpg"
                },
                {
                    "label": "Medium",
                    "height": "500",
                    "width": "375",
                    "url": "https://farm5.staticflickr.com/4497/24096057338_f00c2c0a03.jpg"
                },
                {
                    "label": "Medium 640",
                    "height": "640",
                    "width": "480",
                    "url": "https://farm5.staticflickr.com/4497/24096057338_f00c2c0a03_z.jpg"
                },
                {
                    "label": "Medium 800",
                    "height": "800",
                    "width": 600,
                    "url": "https://farm5.staticflickr.com/4497/24096057338_f00c2c0a03_c.jpg"
                },
                {
                    "label": "Large",
                    "height": "1024",
                    "width": "768",
                    "url": "https://farm5.staticflickr.com/4497/24096057338_f00c2c0a03_b.jpg"
                },
                {
                    "label": "Large 1600",
                    "height": "1600",
                    "width": 1200,
                    "url": "https://farm5.staticflickr.com/4497/24096057338_bc16927814_h.jpg"
                },
                {
                    "label": "Large 2048",
                    "height": "2048",
                    "width": 1536,
                    "url": "https://farm5.staticflickr.com/4497/24096057338_854236b02e_k.jpg"
                },
                {
                    "label": "Original",
                    "height": "4093",
                    "width": "3070",
                    "url": "https://farm5.staticflickr.com/4497/24096057338_2a7d44c39f_o.jpg"
                }
            ]
        },
        {
            "id": "37237722554",
            "title": "Sara y Chema",
            "tags": "",
            "sizes": [
                {
                    "label": "Square",
                    "height": 75,
                    "width": 75,
                    "url": "https://farm5.staticflickr.com/4506/37237722554_a5d7c208b5_s.jpg"
                },
                {
                    "label": "Large Square",
                    "height": "150",
                    "width": "150",
                    "url": "https://farm5.staticflickr.com/4506/37237722554_a5d7c208b5_q.jpg"
                },
                {
                    "label": "Thumbnail",
                    "height": "100",
                    "width": "75",
                    "url": "https://farm5.staticflickr.com/4506/37237722554_a5d7c208b5_t.jpg"
                },
                {
                    "label": "Small",
                    "height": "240",
                    "width": "180",
                    "url": "https://farm5.staticflickr.com/4506/37237722554_a5d7c208b5_m.jpg"
                },
                {
                    "label": "Small 320",
                    "height": "320",
                    "width": 240,
                    "url": "https://farm5.staticflickr.com/4506/37237722554_a5d7c208b5_n.jpg"
                },
                {
                    "label": "Medium",
                    "height": "500",
                    "width": "375",
                    "url": "https://farm5.staticflickr.com/4506/37237722554_a5d7c208b5.jpg"
                },
                {
                    "label": "Medium 640",
                    "height": "640",
                    "width": "480",
                    "url": "https://farm5.staticflickr.com/4506/37237722554_a5d7c208b5_z.jpg"
                },
                {
                    "label": "Medium 800",
                    "height": "800",
                    "width": 600,
                    "url": "https://farm5.staticflickr.com/4506/37237722554_a5d7c208b5_c.jpg"
                },
                {
                    "label": "Large",
                    "height": "1024",
                    "width": "768",
                    "url": "https://farm5.staticflickr.com/4506/37237722554_a5d7c208b5_b.jpg"
                },
                {
                    "label": "Large 1600",
                    "height": "1600",
                    "width": 1200,
                    "url": "https://farm5.staticflickr.com/4506/37237722554_d8fa2d7435_h.jpg"
                },
                {
                    "label": "Large 2048",
                    "height": "2048",
                    "width": 1536,
                    "url": "https://farm5.staticflickr.com/4506/37237722554_53bc06596b_k.jpg"
                },
                {
                    "label": "Original",
                    "height": "4204",
                    "width": "3153",
                    "url": "https://farm5.staticflickr.com/4506/37237722554_0498bfee5c_o.jpg"
                }
            ]
        },
        {
            "id": "26171583139",
            "title": "Sara y Chema",
            "tags": "",
            "sizes": [
                {
                    "label": "Square",
                    "height": 75,
                    "width": 75,
                    "url": "https://farm5.staticflickr.com/4477/26171583139_e2d79f7de0_s.jpg"
                },
                {
                    "label": "Large Square",
                    "height": "150",
                    "width": "150",
                    "url": "https://farm5.staticflickr.com/4477/26171583139_e2d79f7de0_q.jpg"
                },
                {
                    "label": "Thumbnail",
                    "height": "100",
                    "width": "75",
                    "url": "https://farm5.staticflickr.com/4477/26171583139_e2d79f7de0_t.jpg"
                },
                {
                    "label": "Small",
                    "height": "240",
                    "width": "180",
                    "url": "https://farm5.staticflickr.com/4477/26171583139_e2d79f7de0_m.jpg"
                },
                {
                    "label": "Small 320",
                    "height": "320",
                    "width": 240,
                    "url": "https://farm5.staticflickr.com/4477/26171583139_e2d79f7de0_n.jpg"
                },
                {
                    "label": "Medium",
                    "height": "500",
                    "width": "375",
                    "url": "https://farm5.staticflickr.com/4477/26171583139_e2d79f7de0.jpg"
                },
                {
                    "label": "Medium 640",
                    "height": "640",
                    "width": "480",
                    "url": "https://farm5.staticflickr.com/4477/26171583139_e2d79f7de0_z.jpg"
                },
                {
                    "label": "Medium 800",
                    "height": "800",
                    "width": 600,
                    "url": "https://farm5.staticflickr.com/4477/26171583139_e2d79f7de0_c.jpg"
                },
                {
                    "label": "Large",
                    "height": "1024",
                    "width": "768",
                    "url": "https://farm5.staticflickr.com/4477/26171583139_e2d79f7de0_b.jpg"
                },
                {
                    "label": "Large 1600",
                    "height": "1600",
                    "width": 1200,
                    "url": "https://farm5.staticflickr.com/4477/26171583139_5913e62e0b_h.jpg"
                },
                {
                    "label": "Large 2048",
                    "height": "2048",
                    "width": 1536,
                    "url": "https://farm5.staticflickr.com/4477/26171583139_f6276c3c5a_k.jpg"
                },
                {
                    "label": "Original",
                    "height": "4515",
                    "width": "3386",
                    "url": "https://farm5.staticflickr.com/4477/26171583139_13aa00bf91_o.jpg"
                }
            ]
        },
        {
            "id": "37916335822",
            "title": "Sara y Chema",
            "tags": "",
            "sizes": [
                {
                    "label": "Square",
                    "height": 75,
                    "width": 75,
                    "url": "https://farm5.staticflickr.com/4490/37916335822_efb2464391_s.jpg"
                },
                {
                    "label": "Large Square",
                    "height": "150",
                    "width": "150",
                    "url": "https://farm5.staticflickr.com/4490/37916335822_efb2464391_q.jpg"
                },
                {
                    "label": "Thumbnail",
                    "height": "70",
                    "width": "100",
                    "url": "https://farm5.staticflickr.com/4490/37916335822_efb2464391_t.jpg"
                },
                {
                    "label": "Small",
                    "height": "167",
                    "width": "240",
                    "url": "https://farm5.staticflickr.com/4490/37916335822_efb2464391_m.jpg"
                },
                {
                    "label": "Small 320",
                    "height": 223,
                    "width": "320",
                    "url": "https://farm5.staticflickr.com/4490/37916335822_efb2464391_n.jpg"
                },
                {
                    "label": "Medium",
                    "height": "348",
                    "width": "500",
                    "url": "https://farm5.staticflickr.com/4490/37916335822_efb2464391.jpg"
                },
                {
                    "label": "Medium 640",
                    "height": "445",
                    "width": "640",
                    "url": "https://farm5.staticflickr.com/4490/37916335822_efb2464391_z.jpg"
                },
                {
                    "label": "Medium 800",
                    "height": 556,
                    "width": "800",
                    "url": "https://farm5.staticflickr.com/4490/37916335822_efb2464391_c.jpg"
                },
                {
                    "label": "Large",
                    "height": "712",
                    "width": "1024",
                    "url": "https://farm5.staticflickr.com/4490/37916335822_efb2464391_b.jpg"
                },
                {
                    "label": "Large 1600",
                    "height": 1113,
                    "width": "1600",
                    "url": "https://farm5.staticflickr.com/4490/37916335822_8ea167da25_h.jpg"
                },
                {
                    "label": "Large 2048",
                    "height": 1425,
                    "width": "2048",
                    "url": "https://farm5.staticflickr.com/4490/37916335822_29c4afd0e9_k.jpg"
                },
                {
                    "label": "Original",
                    "height": "3206",
                    "width": "4608",
                    "url": "https://farm5.staticflickr.com/4490/37916335822_039475f009_o.jpg"
                }
            ]
        },
        {
            "id": "26171581209",
            "title": "Sara y Chema",
            "tags": "",
            "sizes": [
                {
                    "label": "Square",
                    "height": 75,
                    "width": 75,
                    "url": "https://farm5.staticflickr.com/4500/26171581209_49599832bb_s.jpg"
                },
                {
                    "label": "Large Square",
                    "height": "150",
                    "width": "150",
                    "url": "https://farm5.staticflickr.com/4500/26171581209_49599832bb_q.jpg"
                },
                {
                    "label": "Thumbnail",
                    "height": "100",
                    "width": "75",
                    "url": "https://farm5.staticflickr.com/4500/26171581209_49599832bb_t.jpg"
                },
                {
                    "label": "Small",
                    "height": "240",
                    "width": "180",
                    "url": "https://farm5.staticflickr.com/4500/26171581209_49599832bb_m.jpg"
                },
                {
                    "label": "Small 320",
                    "height": "320",
                    "width": 240,
                    "url": "https://farm5.staticflickr.com/4500/26171581209_49599832bb_n.jpg"
                },
                {
                    "label": "Medium",
                    "height": "500",
                    "width": "375",
                    "url": "https://farm5.staticflickr.com/4500/26171581209_49599832bb.jpg"
                },
                {
                    "label": "Medium 640",
                    "height": "640",
                    "width": "480",
                    "url": "https://farm5.staticflickr.com/4500/26171581209_49599832bb_z.jpg"
                },
                {
                    "label": "Medium 800",
                    "height": "800",
                    "width": 600,
                    "url": "https://farm5.staticflickr.com/4500/26171581209_49599832bb_c.jpg"
                },
                {
                    "label": "Large",
                    "height": "1024",
                    "width": "768",
                    "url": "https://farm5.staticflickr.com/4500/26171581209_49599832bb_b.jpg"
                },
                {
                    "label": "Large 1600",
                    "height": "1600",
                    "width": 1200,
                    "url": "https://farm5.staticflickr.com/4500/26171581209_8fe4a8b5b4_h.jpg"
                },
                {
                    "label": "Large 2048",
                    "height": "2048",
                    "width": 1536,
                    "url": "https://farm5.staticflickr.com/4500/26171581209_b2095db05e_k.jpg"
                },
                {
                    "label": "Original",
                    "height": "4217",
                    "width": "3163",
                    "url": "https://farm5.staticflickr.com/4500/26171581209_a2973e33b3_o.jpg"
                }
            ]
        },
        {
            "id": "26171579689",
            "title": "Sara y Chema",
            "tags": "",
            "sizes": [
                {
                    "label": "Square",
                    "height": 75,
                    "width": 75,
                    "url": "https://farm5.staticflickr.com/4459/26171579689_efc57bd17b_s.jpg"
                },
                {
                    "label": "Large Square",
                    "height": "150",
                    "width": "150",
                    "url": "https://farm5.staticflickr.com/4459/26171579689_efc57bd17b_q.jpg"
                },
                {
                    "label": "Thumbnail",
                    "height": "75",
                    "width": "100",
                    "url": "https://farm5.staticflickr.com/4459/26171579689_efc57bd17b_t.jpg"
                },
                {
                    "label": "Small",
                    "height": "180",
                    "width": "240",
                    "url": "https://farm5.staticflickr.com/4459/26171579689_efc57bd17b_m.jpg"
                },
                {
                    "label": "Small 320",
                    "height": 240,
                    "width": "320",
                    "url": "https://farm5.staticflickr.com/4459/26171579689_efc57bd17b_n.jpg"
                },
                {
                    "label": "Medium",
                    "height": "375",
                    "width": "500",
                    "url": "https://farm5.staticflickr.com/4459/26171579689_efc57bd17b.jpg"
                },
                {
                    "label": "Medium 640",
                    "height": "480",
                    "width": "640",
                    "url": "https://farm5.staticflickr.com/4459/26171579689_efc57bd17b_z.jpg"
                },
                {
                    "label": "Medium 800",
                    "height": 600,
                    "width": "800",
                    "url": "https://farm5.staticflickr.com/4459/26171579689_efc57bd17b_c.jpg"
                },
                {
                    "label": "Large",
                    "height": "768",
                    "width": "1024",
                    "url": "https://farm5.staticflickr.com/4459/26171579689_efc57bd17b_b.jpg"
                },
                {
                    "label": "Large 1600",
                    "height": 1200,
                    "width": "1600",
                    "url": "https://farm5.staticflickr.com/4459/26171579689_a087927177_h.jpg"
                },
                {
                    "label": "Large 2048",
                    "height": 1536,
                    "width": "2048",
                    "url": "https://farm5.staticflickr.com/4459/26171579689_ae2e6e062d_k.jpg"
                },
                {
                    "label": "Original",
                    "height": "3456",
                    "width": "4608",
                    "url": "https://farm5.staticflickr.com/4459/26171579689_bcace55874_o.jpg"
                }
            ]
        }
    ]
}